backend/__init__.py
backend/main.py
backend/scraper_service.py
exam_downloader-0.2.0.dist-info/licenses/LICENSE
exam_downloader-0.2.0.dist-info/METADATA
exam_downloader-0.2.0.dist-info/WHEEL
exam_downloader-0.2.0.dist-info/entry_points.txt
exam_downloader-0.2.0.dist-info/top_level.txt
exam_downloader-0.2.0.dist-info/RECORD
