Metadata-Version: 2.4
Name: exam_downloader
Version: 0.2.0
Summary: A premium full-stack platform for downloading CAIE and Edexcel exam papers.
Home-page: https://github.com/fam007e/examquest
Author: Faisal Ahmed Moshiur
Author-email: faisalmoshiur+gitpy@gmail.com
License: MIT
Keywords: education,exams,cambridge,edexcel,igcse,a-level,papacambridge,xtremepapers
Classifier: Programming Language :: Python :: 3
Classifier: License :: OSI Approved :: MIT License
Classifier: Operating System :: OS Independent
Classifier: Topic :: Education
Classifier: Topic :: Internet :: WWW/HTTP
Classifier: Topic :: Utilities
Requires-Python: >=3.6
License-File: LICENSE
Requires-Dist: requests>=2.25.1
Requires-Dist: beautifulsoup4>=4.9.3
Requires-Dist: aiohttp>=3.8.1
Requires-Dist: fastapi>=0.127.0
Requires-Dist: uvicorn>=0.35.0
Dynamic: author
Dynamic: author-email
Dynamic: classifier
Dynamic: description
Dynamic: description-content-type
Dynamic: home-page
Dynamic: keywords
Dynamic: license
Dynamic: license-file
Dynamic: requires-dist
Dynamic: requires-python
Dynamic: summary
